compose_pydantic/__init__.py
compose_pydantic/lib.py
compose_pydantic/models.py
compose_pydantic-0.2.1.dist-info/LICENSE
compose_pydantic-0.2.1.dist-info/METADATA
compose_pydantic-0.2.1.dist-info/WHEEL
compose_pydantic-0.2.1.dist-info/top_level.txt
compose_pydantic-0.2.1.dist-info/RECORD
