Metadata-Version: 2.1
Name: compose-pydantic
Version: 0.2.1
Summary: Parse Compose Specification data using Pydantic
Home-page: https://github.com/alexmon/compose-pydantic
Author: Alexandros Monastiriotis
Author-email: alexmondev@gmail.com
License: MIT
Keywords: Compose,Pydantic
Classifier: Development Status :: 1 - Planning
Classifier: Intended Audience :: Developers
Classifier: License :: OSI Approved :: MIT License
Classifier: Natural Language :: English
Classifier: Operating System :: OS Independent
Classifier: Programming Language :: Python :: 3
Classifier: Topic :: Software Development
Classifier: Topic :: Software Development :: Code Generators
License-File: LICENSE
Requires-Dist: pydantic ==1.9.0
Requires-Dist: PyYAML >=6.0
Requires-Dist: mergedeep >=1.3.4
Provides-Extra: dev
Requires-Dist: IPython ; extra == 'dev'
Provides-Extra: testing
Requires-Dist: IPython ; extra == 'testing'
Requires-Dist: tox ; extra == 'testing'
Requires-Dist: pytest ; extra == 'testing'
Requires-Dist: pytest-cov ; extra == 'testing'
Requires-Dist: mock ; extra == 'testing'
Requires-Dist: flake8 ==5.0.4 ; extra == 'testing'
